<!-- Natalia García Ortega y Fernando Lanzarot Facio-->
<?xml version="1.0" encoding="UTF-8"?>
<!DOCTYPE videojuego SYSTEM "videojuego.dtd">

<videojuegos>
  <!-- Doki Doki Literature Club -->
  <videojuego>
    <titulo>Doki Doki Literature Club!</titulo>
    <subtitulo>DDLC</subtitulo>
    <generos>
      <genero>Visual Novel</genero>
      <genero>Terror Psicológico</genero>
    </generos>
    <plataformas>
      <plataforma>PC</plataforma>
      <plataforma>Mac</plataforma>
      <plataforma>Linux</plataforma>
    </plataformas>
    <fecha_lanzamiento>2017-09-22</fecha_lanzamiento>
    <desarrollador>Team Salvato</desarrollador>
    <distribuidor>Team Salvato</distribuidor>
    <version>1.1.1</version>
    <descripcion>Una novela visual con apariencia de simulador de citas que esconde un trasfondo perturbador y de terror psicológico.</descripcion>
    <modos>
      <modo>Un jugador</modo>
    </modos>
    <clasificacion>Mature 17+</clasificacion>
    <idiomas>
      <idioma>Inglés</idioma>
    </idiomas>
    <extras>
      <logros/>
      <expansiones/>
      <motor>Ren'Py</motor>
      <disponibilidad>Gratuito en Steam e itch.io</disponibilidad>
      <puntuacion>Muy Positivas (Steam)</puntuacion>
    </extras>
  </videojuego>

  <!-- Hollow Knight -->
  <videojuego>
    <titulo>Hollow Knight</titulo>
    <generos>
      <genero>Metroidvania</genero>
      <genero>Acción</genero>
      <genero>Aventura</genero>
    </generos>
    <plataformas>
      <plataforma>PC</plataforma>
      <plataforma>Nintendo Switch</plataforma>
      <plataforma>PS4</plataforma>
      <plataforma>Xbox One</plataforma>
    </plataformas>
    <fecha_lanzamiento>2017-02-24</fecha_lanzamiento>
    <desarrollador>Team Cherry</desarrollador>
    <distribuidor>Team Cherry</distribuidor>
    <descripcion>Un desafiante metroidvania en un vasto mundo subterráneo lleno de misterios, combates intensos y exploración.</descripcion>
    <modos>
      <modo>Un jugador</modo>
    </modos>
    <clasificacion>PEGI 7</clasificacion>
    <idiomas>
      <idioma>Inglés</idioma>
      <idioma>Español</idioma>
      <idioma>Francés</idioma>
      <idioma>Alemán</idioma>
    </idiomas>
    <duracion>30-60 horas</duracion>
    <extras>
      <expansiones>
        <expansion>Hidden Dreams</expansion>
        <expansion>The Grimm Troupe</expansion>
        <expansion>Lifeblood</expansion>
        <expansion>Godmaster</expansion>
      </expansiones>
      <motor>Unity</motor>
      <puntuacion>Muy Positivas (Steam)</puntuacion>
    </extras>
  </videojuego>

  <!-- Inscryption -->
  <videojuego>
    <titulo>Inscryption</titulo>
    <generos>
      <genero>Cartas</genero>
      <genero>Puzzle</genero>
      <genero>Terror Psicológico</genero>
    </generos>
    <plataformas>
      <plataforma>PC</plataforma>
      <plataforma>PS4</plataforma>
      <plataforma>PS5</plataforma>
      <plataforma>Nintendo Switch</plataforma>
    </plataformas>
    <fecha_lanzamiento>2021-10-19</fecha_lanzamiento>
    <desarrollador>Daniel Mullins Games</desarrollador>
    <distribuidor>Devolver Digital</distribuidor>
    <descripcion>Un juego de cartas roguelike con acertijos, narrativa oscura y elementos de terror psicológico.</descripcion>
    <modos>
      <modo>Un jugador</modo>
    </modos>
    <clasificacion>PEGI 16</clasificacion>
    <idiomas>
      <idioma>Inglés</idioma>
      <idioma>Español</idioma>
      <idioma>Francés</idioma>
      <idioma>Alemán</idioma>
    </idiomas>
    <extras>
      <motor>Unity</motor>
      <puntuacion>Muy Positivas (Steam)</puntuacion>
    </extras>
  </videojuego>

  <!-- Mouthwashing -->
  <videojuego>
    <titulo>Mouthwashing</titulo>
    <generos>
      <genero>Terror Psicológico</genero>
      <genero>Indie</genero>
    </generos>
    <plataformas>
      <plataforma>PC</plataforma>
    </plataformas>
    <fecha_lanzamiento>2023</fecha_lanzamiento>
    <desarrollador>Mossin</desarrollador>
    <distribuidor>Mossin</distribuidor>
    <descripcion>Un juego indie de terror psicológico con atmósfera inquietante y narrativa experimental.</descripcion>
    <modos>
      <modo>Un jugador</modo>
    </modos>
    <clasificacion>No clasificado</clasificacion>
    <idiomas>
      <idioma>Inglés</idioma>
    </idiomas>
    <extras>
      <puntuacion>Positivas (Steam)</puntuacion>
    </extras>
  </videojuego>

  <!-- Welcome to the Game -->
  <videojuego>
    <titulo>Welcome to the Game</titulo>
    <generos>
      <genero>Terror</genero>
      <genero>Puzzle</genero>
      <genero>Horror de Exploración</genero>
    </generos>
    <plataformas>
      <plataforma>PC</plataforma>
    </plataformas>
    <fecha_lanzamiento>2016-06-15</fecha_lanzamiento>
    <desarrollador>Reflect Studios</desarrollador>
    <distribuidor>Reflect Studios</distribuidor>
    <descripcion>Un juego de terror y acertijos centrado en explorar la deep web desde un entorno simulado con tensión constante.</descripcion>
    <modos>
      <modo>Un jugador</modo>
    </modos>
    <clasificacion>Mature 17+</clasificacion>
    <idiomas>
      <idioma>Inglés</idioma>
    </idiomas>
    <extras>
      <puntuacion>Mixtas (Steam)</puntuacion>
    </extras>
  </videojuego>
</videojuegos>
